{
  "start_date": "2026-01-01",
  "end_date": "2026-03-31",
  "total_days": 90,
  "profit_days": 21,
  "loss_days": 43,
  "capital": 5000.0,
  "end_balance": 4995.97022,
  "max_drawdown": -3.9037600000001476,
  "max_ddpercent": -0.07807730793116247,
  "max_drawdown_duration": 88,
  "total_net_pnl": -4.02978000000006,
  "daily_net_pnl": -0.044775333333334,
  "total_commission": 0.0,
  "daily_commission": 0.0,
  "total_slippage": 0.0,
  "daily_slippage": 0.0,
  "total_turnover": 8788.819420000002,
  "daily_turnover": 97.65354911111113,
  "total_trade_count": 1144,
  "daily_trade_count": 12.71111111111111,
  "total_return": -0.08059559999999966,
  "annual_return": -0.21492159999999907,
  "daily_return": -0.0008958677301662522,
  "return_std": 0.0022159271428006245,
  "sharpe_ratio": -6.263167650816063,
  "ewm_sharpe": -6.276345385683278,
  "return_drawdown_ratio": -1.0322538281040308,
  "rgr_ratio": -4.677991703294001,
  "warning": "标准 vn.py CTA BacktestingEngine 未自动计入 OKX perpetual funding fee，本结果仅包含价格盈亏、手续费、滑点等常规项。",
  "bankrupt": false,
  "statistics_valid": true,
  "invalid_reason": null,
  "engine_trade_count": 1144,
  "order_count": 1162,
  "closed_round_trip_count": 572,
  "statistics_total_trade_count": 1144,
  "win_rate": 32.86713286713287,
  "profit_loss_ratio": 1.2210248827854464,
  "average_win": 0.03185851063829774,
  "average_loss": 0.026091614583333426,
  "gross_profit": 5.989399999999976,
  "gross_loss": 10.019180000000036,
  "first_bankrupt_date": null,
  "final_balance": 4995.97022,
  "min_balance": 4995.96125,
  "max_balance": 4999.86501
}