{
  "T": "p97",
  "rule": "C2",
  "n": 21298,
  "net": 187725.48379094462,
  "pf": 2.0636,
  "win": 0.4828,
  "max_dd": 2328.48,
  "dd_over_net": 0.0124,
  "avg_notional": 2289.9,
  "max_notional": 4285.6,
  "max_single_loss": -1336.32,
  "dPnL_pct_vs_v2b": -35.33,
  "dPnL_pct_vs_flat": -0.79,
  "dd_x_flat": 1.0349,
  "cap_count": 1468,
  "cap_trigger_rate": 0.0689,
  "triggered_base_pnl_sum": 153200.27,
  "triggered_base_pnl_mean": 104.36,
  "triggered_base_pnl_std": 369.24,
  "triggered_net_positive": true,
  "dd_culprit_total": 16,
  "dd_culprit_hit": 2,
  "dd_culprit_hit_rate": 0.125,
  "gate1_dd": true,
  "gate2_pnl": false,
  "pass_both": false
}