{
  "start_date": "2025-01-01",
  "end_date": "2026-03-31",
  "total_days": 455,
  "profit_days": 157,
  "loss_days": 293,
  "capital": 5000.0,
  "end_balance": 4975.6646,
  "max_drawdown": -24.34827000000041,
  "max_ddpercent": -0.48696721443984914,
  "max_drawdown_duration": 453,
  "total_net_pnl": -24.33540000000034,
  "daily_net_pnl": -0.053484395604396356,
  "total_commission": 0.0,
  "daily_commission": 0.0,
  "total_slippage": 0.0,
  "daily_slippage": 0.0,
  "total_turnover": 69629.55506,
  "daily_turnover": 153.03198914285713,
  "total_trade_count": 7146,
  "daily_trade_count": 15.705494505494505,
  "total_return": -0.48670800000000236,
  "annual_return": -0.2567250989011001,
  "daily_return": -0.0010722995177846139,
  "return_std": 0.0029135329414714194,
  "sharpe_ratio": -5.701666338364677,
  "ewm_sharpe": -5.73703643241327,
  "return_drawdown_ratio": -0.9994676963209013,
  "rgr_ratio": -1.4335403243990972,
  "warning": "标准 vn.py CTA BacktestingEngine 未自动计入 OKX perpetual funding fee，本结果仅包含价格盈亏、手续费、滑点等常规项。",
  "bankrupt": false,
  "statistics_valid": true,
  "invalid_reason": null,
  "engine_trade_count": 7146,
  "order_count": 7250,
  "closed_round_trip_count": 3573,
  "statistics_total_trade_count": 7146,
  "win_rate": 35.12454520011195,
  "profit_loss_ratio": 1.2525296001205581,
  "average_win": 0.04101980876494012,
  "average_loss": 0.03274957235421175,
  "gross_profit": 51.47985999999985,
  "gross_loss": 75.8152600000002,
  "first_bankrupt_date": null,
  "final_balance": 4975.6646,
  "min_balance": 4975.6331,
  "max_balance": 4999.98137
}